zdb2/__cls_aide_rst_base__.py
zdb2/__cls_aide_sql_pgs__.py
zdb2/__cls_db2_conn__.py
zdb2/__init__.py
zdb2-3.2.dist-info/LICENSE
zdb2-3.2.dist-info/METADATA
zdb2-3.2.dist-info/WHEEL
zdb2-3.2.dist-info/top_level.txt
zdb2-3.2.dist-info/RECORD
